COPYRIGHT
crawl_classic/__init__.py
crawl_classic/crit.py
crawl_classic/equipment.py
crawl_classic/occupations.py
crawl_classic/weapon.py
crawl_classic-0.1.2.dist-info/LICENSE
crawl_classic-0.1.2.dist-info/WHEEL
crawl_classic-0.1.2.dist-info/METADATA
crawl_classic-0.1.2.dist-info/RECORD
