Metadata-Version: 2.1
Name: crawl-classic
Version: 0.1.2
Summary: Random tables for Dungeon Crawl Classics RPG.
Home-page: https://github.com/sethwoodworth/crawl-classic
Keywords: RPG,OGL
Author: Seth Woodworth
Author-email: seth@sethish.com
Requires-Python: >=3.7,<4.0
Classifier: Development Status :: 3 - Alpha
Classifier: Intended Audience :: Developers
Classifier: License :: Other/Proprietary License
Classifier: Natural Language :: English
Classifier: Programming Language :: Python :: 3
Classifier: Programming Language :: Python :: 3 :: Only
Classifier: Programming Language :: Python :: 3.7
Classifier: Topic :: Games/Entertainment :: Role-Playing
Classifier: Typing :: Typed
Project-URL: Repository, https://github.com/sethwoodworth/crawl-classic
